{
  "sliders": ["Bikes.png", "heatrers.png", "Third-slide.png"],
  "bicycles": [
    {
      "id": 1,
      "title": "Road bike",
      "details": "Lorem ipsum is placeholder text commonly used in the graphic, print, and publishing industries for previewing layouts and visual mockups.",
      "price": "20$",
      "src": "/imgs/bicycle/road-bike.jpeg"
    },
    {
      "id": 2,
      "title": "Electric bike",
      "details": "Lorem ipsum is placeholder text commonly used in the graphic, print, and publishing industries for previewing layouts and visual mockups.",
      "price": "20$",
      "src": "/imgs/bicycle/elec-bike.jpeg"
    },
    {
      "id": 3,
      "title": "Cross bike",
      "details": "Lorem ipsum is placeholder text commonly used in the graphic, print, and publishing industries for previewing layouts and visual mockups.",
      "price": "20$",
      "src": "/imgs/bicycle/cross-bike.jpeg"
    },
    {
      "id": 4,
      "title": "kids bike",
      "details": "Lorem ipsum is placeholder text commonly used in the graphic, print, and publishing industries for previewing layouts and visual mockups.",
      "price": "20$",
      "src": "/imgs/bicycle/kid-mount.jpeg"
    }
  ],
  "heaters": [
    {
      "id": 1,
      "title": "Corona",
      "details": "Lorem ipsum is placeholder text commonly used in the graphic, print, and publishing industries for previewing layouts and visual mockups.",
      "price": "20$",
      "src": "/imgs/heaters/heat_1.jpeg"
    },
    {
      "id": 2,
      "title": "Toyotomi",
      "details": "Lorem ipsum is placeholder text commonly used in the graphic, print, and publishing industries for previewing layouts and visual mockups.",
      "price": "20$",
      "src": "/imgs/heaters/heat_2.jpeg"
    },
    {
      "id": 3,
      "title": "Toyotomi",
      "details": "",
      "price": "20$",
      "src": "/imgs/heaters/heat_3.jpeg"
    },
    {
      "id": 4,
      "title": "Corona",
      "details": "Lorem ipsum is placeholder text commonly used in the graphic, print, and publishing industries for previewing layouts and visual mockups.",
      "price": "20$",
      "src": "/imgs/heaters/heat_4.jpeg"
    }
  ]
}
